echowave/__init__.py
echowave/__version__.py
echowave/builtins.py
echowave/coloring.py
echowave/echowave.py
echowave-0.1.1.dist-info/METADATA
echowave-0.1.1.dist-info/WHEEL
echowave-0.1.1.dist-info/top_level.txt
echowave-0.1.1.dist-info/RECORD
