Metadata-Version: 2.1
Name: echowave
Version: 0.1.1
Summary: A cloned version of the IceCream package that replaces print() with ic() when debugging.
Author: Torrez Tsoi
Author-email: that1.stinkyarmpits@gmail.com
Classifier: Programming Language :: Python :: 3
Classifier: License :: OSI Approved :: MIT License
Classifier: Operating System :: OS Independent
Requires-Python: >=3.9
